pyutilscripts/__init__.py
pyutilscripts/fcopy.py
pyutilscripts/forward_tcp.py
pyutilscripts/httpd.py
pyutilscripts/prunedirs.py
pyutilscripts/toast.py
pyutilscripts/utils/__init__.py
pyutilscripts-0.9.0.dist-info/licenses/LICENSE
pyutilscripts-0.9.0.dist-info/METADATA
pyutilscripts-0.9.0.dist-info/WHEEL
pyutilscripts-0.9.0.dist-info/entry_points.txt
pyutilscripts-0.9.0.dist-info/top_level.txt
pyutilscripts-0.9.0.dist-info/RECORD
