Metadata-Version: 2.4
Name: pyutilscripts
Version: 0.9.0
Summary: PyUtilScripts 是一个基于 Python 的通用小工具集合，目标是提供编写通用任务的辅助工具。
Author-email: Zero Kwok <zero.kwok@foxmail.com>
License: MIT License
Project-URL: Homepage, https://github.com/ZeroKwok/pyutilscripts
Project-URL: Issues, https://github.com/ZeroKwok/pyutilscripts/issues
Keywords: tools
Classifier: Intended Audience :: Developers
Classifier: Topic :: Software Development :: Build Tools
Classifier: Programming Language :: Python
Classifier: Programming Language :: Python :: 3 :: Only
Classifier: Programming Language :: Python :: 3
Classifier: Programming Language :: Python :: 3.7
Classifier: Programming Language :: Python :: 3.8
Classifier: Programming Language :: Python :: 3.9
Classifier: Programming Language :: Python :: 3.10
Classifier: Programming Language :: Python :: 3.11
Requires-Python: >=3.7
License-File: LICENSE
Requires-Dist: click
Requires-Dist: natsort
Requires-Dist: termcolor
Provides-Extra: dev
Requires-Dist: pytest; extra == "dev"
Requires-Dist: pytest-cov; extra == "dev"
Dynamic: license-file
